simple_hypercore_protocol/__init__.py
simple_hypercore_protocol/schema.proto
simple_hypercore_protocol/schema_pb2.py
simple_hypercore_protocol-0.0.1a2.dist-info/LICENSE
simple_hypercore_protocol-0.0.1a2.dist-info/WHEEL
simple_hypercore_protocol-0.0.1a2.dist-info/METADATA
simple_hypercore_protocol-0.0.1a2.dist-info/RECORD
